optime/__init__.py
optime/ga.py
optime-0.0.1.dist-info/LICENSE
optime-0.0.1.dist-info/METADATA
optime-0.0.1.dist-info/WHEEL
optime-0.0.1.dist-info/top_level.txt
optime-0.0.1.dist-info/RECORD
