Metadata-Version: 2.1
Name: optime
Version: 0.0.1
Summary: Quick and simple optimization package. First implemented: A genetic algorithm (GA).
Author-email: Maarten Tytgat <maarten.tytgat@gmail.com>
Project-URL: Homepage, https://github.com/mtyt/optime
Classifier: Programming Language :: Python :: 3
Classifier: License :: OSI Approved :: MIT License
Classifier: Operating System :: OS Independent
Requires-Python: >=3.7
License-File: LICENSE
Requires-Dist: numpy (>=1.23.4)
Requires-Dist: pandas (>=1.5.1)
Requires-Dist: matplotlib (>=3.6.2)
